[
  {
    "_id": {
      "$oid": "665105dade242e84893090b6"
    },
    "label": "Hack4Values #1 place",
    "value": 50,
    "createdAt": {
      "$date": "2024-05-24T21:25:46.893Z"
    },
    "updatedAt": {
      "$date": "2024-05-24T21:25:46.893Z"
    },
    "__v": 0,
    "teamId": "6a046a42a8a0b7fa201dba0c"
  },
  {
    "_id": {
      "$oid": "66510624de242e8489309247"
    },
    "label": "Hack4Values #2 place",
    "value": 45,
    "createdAt": {
      "$date": "2024-05-24T21:27:00.658Z"
    },
    "updatedAt": {
      "$date": "2024-05-24T21:27:00.658Z"
    },
    "__v": 0,
    "teamId": "6a046a42a8a0b7fa201dba09"
  },
  {
    "_id": {
      "$oid": "66510648de242e848930938f"
    },
    "label": "Hack4Values #3 place",
    "value": 40,
    "createdAt": {
      "$date": "2024-05-24T21:27:36.454Z"
    },
    "updatedAt": {
      "$date": "2024-05-24T21:27:36.454Z"
    },
    "__v": 0,
    "teamId": "6a046a42a8a0b7fa201db9fd"
  },
  {
    "_id": {
      "$oid": "66510664de242e84893094c3"
    },
    "label": "Hack4Values #4 place",
    "value": 35,
    "createdAt": {
      "$date": "2024-05-24T21:28:04.623Z"
    },
    "updatedAt": {
      "$date": "2024-05-24T21:28:04.623Z"
    },
    "__v": 0,
    "teamId": "6a046a42a8a0b7fa201db9f4"
  }
]
